datathon2.py
datathon2-0.1.11.dist-info/LICENSE
datathon2-0.1.11.dist-info/METADATA
datathon2-0.1.11.dist-info/WHEEL
datathon2-0.1.11.dist-info/top_level.txt
datathon2-0.1.11.dist-info/RECORD
