Metadata-Version: 2.1
Name: datathon2
Version: 0.1.11
Summary: datathon2
Home-page: https://github.com/MIT-LCP/datathon-package
Author: UNKNOWN
Author-email: UNKNOWN
License: MIT
Keywords: datathon
Platform: UNKNOWN
Requires-Dist: pandas (>=0.22.0)
Requires-Dist: numpy (>=1.12.1)
Requires-Dist: scikit-learn (>=0.19.0)
Requires-Dist: pydotplus (>=2.0.0)
Requires-Dist: matplotlib (>=2.0.0)
Requires-Dist: tableone (>=0.6.0)
